README.rst
setup.cfg
setup.py
Pantry.egg-info/PKG-INFO
Pantry.egg-info/SOURCES.txt
Pantry.egg-info/dependency_links.txt
Pantry.egg-info/top_level.txt
pantry/__init__.py